{"jobName":"16","accountId":"138509501210","results":{"transcripts":[{"transcript":"Plant Marine War of"}],"items":[{"start_time":"0.04","end_time":"0.29","alternatives":[{"confidence":"0.7513","content":"Plant"}],"type":"pronunciation"},{"start_time":"0.29","end_time":"0.57","alternatives":[{"confidence":"0.9203","content":"Marine"}],"type":"pronunciation"},{"start_time":"0.57","end_time":"0.83","alternatives":[{"confidence":"0.9741","content":"War"}],"type":"pronunciation"},{"start_time":"0.83","end_time":"1.05","alternatives":[{"confidence":"0.8397","content":"of"}],"type":"pronunciation"}]},"status":"COMPLETED"}